{
  "university_id": "constructor_university",
  "university_label": "جامعة كونستركتر",
  "country": "ألمانيا",
  "university_type": "خاصة",
  "country_label": "ألمانيا — جامعة خاصة",

  "programs": [
    {
      "id": "bachelor",
      "label": "بكالوريوس",
      "certificates": [
        { "id": "bachelor_british", "label": "شهادة بريطانية", "file": "bachelor_british.json" },
        { "id": "bachelor_arabic", "label": "شهادات عربية", "file": "bachelor_arabic.json" }
      ]
    },
    {
      "id": "ify",
      "label": "سنة تأسيسية",
      "certificates": [
        { "id": "ify_british", "label": "شهادة بريطانية", "file": "ify_british.json" },
        { "id": "ify_arabic", "label": "شهادات عربية", "file": "ify_arabic.json" }
      ]
    },
    {
      "id": "master",
      "label": "ماجستير",
      "direct_flow": "master",
      "file": "master.json"
    },
    {
      "id": "pre_bachelor",
      "label": "Pre-Bachelor",
      "placeholder": true,
      "placeholder_message": "غير متاح حالياً — سيُضاف قريباً"
    }
  ],

  "comparison_rules": {
    "bachelor_arabic": {
      "category": "bachelor",
      "cert_type": "arabic",
      "label": "بكالوريوس — شهادات عربية",
      "requires_hs": true,
      "requires_bachelor": false,
      "ielts_min": null,
      "sat_required": true,
      "sat_conditional": true,
      "conditions_text": {
        "no_sat": "يحتاج تقديم SAT بدرجة 1200+ قبل 31 ديسمبر",
        "no_ielts": "سيتم ترتيب مقابلة لتقييم اللغة",
        "has_all": "مؤهل للتقديم — المعدل يؤثر على المنحة (3,000 إلى 7,000 يورو)"
      },
      "eligible_note": "الرسوم: 20,000 يورو/سنة"
    },
    "bachelor_british": {
      "category": "bachelor",
      "cert_type": "british",
      "label": "بكالوريوس — شهادة بريطانية",
      "requires_hs": true,
      "requires_bachelor": false,
      "ielts_min": null,
      "sat_required": true,
      "sat_conditional": true,
      "a_level_min": 3,
      "a_level_c_min": 3,
      "conditions_text": {
        "no_sat": "يحتاج تقديم SAT بدرجة 1200+ قبل 31 ديسمبر",
        "no_ielts": "سيتم ترتيب مقابلة لتقييم اللغة",
        "a_level_low": "يحتاج 3 مواد A Level على الأقل",
        "a_level_c_low": "درجات أقل من C — جرّب مسار السنة التأسيسية IFY",
        "has_all": "مؤهل للتقديم — يعتمد على التخصص والمواد"
      },
      "eligible_note": "الرسوم: 20,000 يورو/سنة"
    },
    "ify_arabic": {
      "category": "foundation",
      "cert_type": "arabic",
      "label": "سنة تأسيسية — شهادات عربية",
      "requires_hs": true,
      "requires_bachelor": false,
      "ielts_min": null,
      "conditions_text": {
        "has_all": "مؤهل للسنة التأسيسية — الرسوم: 13,000 يورو"
      }
    },
    "ify_british": {
      "category": "foundation",
      "cert_type": "british",
      "label": "سنة تأسيسية — شهادة بريطانية",
      "requires_hs": true,
      "requires_bachelor": false,
      "ielts_min": null,
      "a_level_min": 3,
      "conditions_text": {
        "a_level_low": "يحتاج 3 مواد A Level على الأقل — قد يحتاج مسار بديل",
        "has_all": "مؤهل للسنة التأسيسية — الرسوم: 13,000 يورو"
      }
    },
    "master": {
      "category": "master",
      "cert_type": "any",
      "label": "ماجستير",
      "requires_hs": false,
      "requires_bachelor": true,
      "ielts_min": null,
      "conditions_text": {
        "no_ielts": "سيتم ترتيب مقابلة لتقييم اللغة",
        "has_all": "مؤهل للتقديم — يحتاج اختيار البرنامج في التقييم التفصيلي"
      }
    }
  }
}
